LICENSE
MANIFEST.in
README.rst
setup.py
compsense/__init__.py
compsense/operators.py
compsense/problems.py
compsense/utilities.py
compsense/algorithms/GPSR.py
compsense/algorithms/TwIST.py
compsense/algorithms/__init__.py
compsense/algorithms/base.py
compsense/data/INFO
compsense/data/prob401_English.wav
compsense/data/prob401_Guitar.wav
compsense/data/prob401_Piano.wav
compsense/data/prob403_Lena512.bmp
compsense/data/prob502_angiogram.mat
compsense/data/prob601_ballsmooth32.png
compsense/data/prob601_ballsmooth64.png
compsense/data/prob602_Soccer_ball.svg
compsense/data/prob602_Soccer_ball.txt
compsense/data/prob602_ball32.png
compsense/data/prob602_ball64.png
compsense/data/prob701_Camera.tif
compsense/data/prob703_FingerA104_8.tif
compsense/data/prob901_seismic.mat
doc/Makefile
doc/make.bat
doc/make_doc_images.py
doc/images/prob701_distorted.png
doc/images/prob701_mse.png
doc/images/prob701_objective.png
doc/images/prob701_original.png
doc/images/prob701_reconstructed.png
doc/source/conf.py
doc/source/index.rst
doc/source/install.rst
doc/source/license.rst
doc/source/reference.rst
doc/source/tutorial.rst
doc/source/_templates/autosummary/class.rst
doc/source/generated/compsense.algorithms.TwIST.rst
doc/source/generated/compsense.algorithms.TwIST_raw.rst
doc/source/generated/compsense.algorithms.algorithmBase.rst
doc/source/generated/compsense.algorithms.algorithmBase.solve.rst
doc/source/generated/compsense.operators.op3DStack.__call__.rst
doc/source/generated/compsense.operators.op3DStack.rst
doc/source/generated/compsense.operators.opBase.__call__.rst
doc/source/generated/compsense.operators.opBase.rst
doc/source/generated/compsense.operators.opBlur.__call__.rst
doc/source/generated/compsense.operators.opBlur.rst
doc/source/generated/compsense.operators.opDCT.rst
doc/source/generated/compsense.operators.opDirac.__call__.rst
doc/source/generated/compsense.operators.opDirac.rst
doc/source/generated/compsense.operators.opFFT2d.rst
