Metadata-Version: 1.1
Name: pycompsense
Version: 0.1.3
Summary: A toolbox for compressed sensing and sparse reconstruction algorithms
Home-page: http://bitbucket.org/amitibo/pycompsense
Author: Amit Aides
Author-email: amitibo@tx.technion.ac.il
License: GPLv3
Keywords: singal processing,sparse representation,compressed sensing,CS,optimization
Platform: UNKNOWN
Classifier: License :: OSI Approved :: GNU General Public License v3 or later (GPLv3+)
Classifier: Development Status :: 2 - Pre-Alpha
Classifier: Topic :: Scientific/Engineering
